sphinx_odoo_autodoc-0.3.3.dist-info/DESCRIPTION.rst
sphinx_odoo_autodoc-0.3.3.dist-info/METADATA
sphinx_odoo_autodoc-0.3.3.dist-info/RECORD
sphinx_odoo_autodoc-0.3.3.dist-info/WHEEL
sphinx_odoo_autodoc-0.3.3.dist-info/metadata.json
sphinx_odoo_autodoc-0.3.3.dist-info/top_level.txt
sphinxodooautodoc/__init__.py
sphinxodooautodoc/ext/__init__.py
sphinxodooautodoc/ext/autodoc.py
