Metadata-Version: 2.0
Name: sphinx-odoo-autodoc
Version: 0.3.3
Summary: Sphinx extension to use autodoc on odoo.addons.*
Home-page: https://github.com/nseinlet/odoo-sphinx-autodoc
Author: Sylvain Garancher
Author-email: sylvain.garancher@syleam.fr
License: LICENSE.txt
Platform: UNKNOWN
Requires: sphinx
Requires-Dist: sphinx
